<?phpxml version="1.0" encoding="utf-8" ?>
<dwsync>
<file name=".editorconfig" server="ftp.rodlover.com//domains/rodlover.com/public_html/" local="130694126060000000" remote="131066410200000000" Dst="0" />
<file name=".gitignore" server="ftp.rodlover.com//domains/rodlover.com/public_html/" local="130694126060000000" remote="131066410200000000" Dst="0" />
<file name="bower.json" server="ftp.rodlover.com//domains/rodlover.com/public_html/" local="130694126060000000" remote="131066410200000000" Dst="0" />
<file name="CONTRIBUTING.md" server="ftp.rodlover.com//domains/rodlover.com/public_html/" local="130694126060000000" remote="131066410200000000" Dst="0" />
<file name="eager.jpg" server="ftp.rodlover.com//domains/rodlover.com/public_html/" local="130694126060000000" remote="131066410200000000" Dst="0" />
<file name="Gruntfile.js" server="ftp.rodlover.com//domains/rodlover.com/public_html/" local="130694126060000000" remote="131066410200000000" Dst="0" />
<file name="HISTORY.md" server="ftp.rodlover.com//domains/rodlover.com/public_html/" local="130694126060000000" remote="131066410200000000" Dst="0" />
<file name="hover.jpg" server="ftp.rodlover.com//domains/rodlover.com/public_html/" local="130694126060000000" remote="131066410200000000" Dst="0" />
<file name="index.html" server="ftp.rodlover.com//domains/rodlover.com/public_html/" local="130694126060000000" remote="131066410200000000" Dst="0" />
<file name="license.txt" server="ftp.rodlover.com//domains/rodlover.com/public_html/" local="130694126060000000" remote="131066410800000000" Dst="0" />
<file name="logo-transparent.png" server="ftp.rodlover.com//domains/rodlover.com/public_html/" local="130694126060000000" remote="131066410800000000" Dst="0" />
<file name="package.json" server="ftp.rodlover.com//domains/rodlover.com/public_html/" local="130694126060000000" remote="131066410800000000" Dst="0" />
<file name="README.md" server="ftp.rodlover.com//domains/rodlover.com/public_html/" local="130694126060000000" remote="131066410800000000" Dst="0" />
</dwsync>